Grafane-0.6.dist-info/METADATA
Grafane-0.6.dist-info/RECORD
Grafane-0.6.dist-info/WHEEL
Grafane-0.6.dist-info/top_level.txt
grafane/__init__.py
grafane/client.py
grafane/settings.py
grafane/tests.py
