Metadata-Version: 2.1
Name: Grafane
Version: 0.6
Summary: UNKNOWN
Home-page: https://gitlab.com/drkloc/grafane
Author: Teofilo Sibileau
Author-email: teo.sibileau@gmail.com
License: Creative Commons Attribution-Noncommercial-Share Alike license
Platform: UNKNOWN
Requires-Dist: certifi (==2018.11.29)
Requires-Dist: chardet (==3.0.4)
Requires-Dist: idna (==2.8)
Requires-Dist: influxdb (==5.2.1)
Requires-Dist: python-dateutil (==2.8.0)
Requires-Dist: pytz (==2018.9)
Requires-Dist: requests (==2.21.0)
Requires-Dist: six (==1.12.0)
Requires-Dist: urllib3 (==1.24.1)
